src/__init__.py
src/main.py
alumathpeergroup25-0.1.0.dist-info/METADATA
alumathpeergroup25-0.1.0.dist-info/WHEEL
alumathpeergroup25-0.1.0.dist-info/top_level.txt
alumathpeergroup25-0.1.0.dist-info/RECORD
